streamtracer-2.5.0.dist-info/RECORD
streamtracer-2.5.0.dist-info/WHEEL
streamtracer-2.5.0.dist-info/METADATA
streamtracer-2.5.0.dist-info/licenses/LICENSE
streamtracer/version.py
streamtracer/_streamtracer_rust.cpython-311-darwin.so
streamtracer/__init__.py
streamtracer/streamline.py
streamtracer/tests/test_streamline.py
streamtracer/tests/__init__.py
