Metadata-Version: 2.4
Name: streamtracer
Version: 2.5.0
Classifier: Development Status :: 5 - Production/Stable
Classifier: Intended Audience :: Science/Research
Classifier: License :: OSI Approved :: GNU General Public License v3 (GPLv3)
Classifier: Natural Language :: English
Classifier: Operating System :: OS Independent
Classifier: Programming Language :: Python
Classifier: Programming Language :: Python :: 3
Classifier: Programming Language :: Python :: 3.10
Classifier: Programming Language :: Python :: 3.11
Classifier: Programming Language :: Python :: 3.12
Classifier: Programming Language :: Python :: 3.13
Classifier: Programming Language :: Python :: 3.14
Classifier: Topic :: Scientific/Engineering :: Physics
Requires-Dist: numpy>=1.26
Requires-Dist: packaging>=21.3
Requires-Dist: pytest ; extra == 'tests'
Requires-Dist: pytest-doctestplus ; extra == 'tests'
Requires-Dist: pytest-cov ; extra == 'tests'
Requires-Dist: pytest-xdist ; extra == 'tests'
Requires-Dist: sphinx ; extra == 'docs'
Requires-Dist: sphinx-automodapi ; extra == 'docs'
Requires-Dist: sphinx-changelog ; extra == 'docs'
Requires-Dist: sunpy-sphinx-theme ; extra == 'docs'
Requires-Dist: packaging ; extra == 'docs'
Requires-Dist: jupyter-sphinx ; extra == 'docs'
Requires-Dist: sphinx-changelog ; extra == 'docs'
Provides-Extra: tests
Provides-Extra: docs
License-File: LICENSE
Summary: Python library to calculate streamlines
Author: David Stansby, Lars Mejnertsen
Author-email: The SunPy Developers <sunpy@googlegroups.com>
Requires-Python: >=3.10
Project-URL: Homepage, https://sunpy.org
Project-URL: Source Code, https://github.com/sunpy/streamtracer
Project-URL: Download, https://pypi.org/project/streamtracer
Project-URL: Documentation, https://docs.sunpy.org/projects/streamtracer
Project-URL: Changelog, https://docs.sunpy.org/projects/streamtracer/en/stable/whatsnew/changelog.html
Project-URL: Issue Tracker, https://github.com/sunpy/streamtracer/issues
